snuggs/__init__.py
snuggs-1.4.6.dist-info/AUTHORS.txt
snuggs-1.4.6.dist-info/LICENSE
snuggs-1.4.6.dist-info/METADATA
snuggs-1.4.6.dist-info/WHEEL
snuggs-1.4.6.dist-info/top_level.txt
snuggs-1.4.6.dist-info/RECORD
