Metadata-Version: 2.1
Name: snuggs
Version: 1.4.6
Summary: Snuggs are s-expressions for Numpy
Home-page: https://github.com/mapbox/snuggs
Author: Sean Gillies
Author-email: sean@mapbox.com
License: MIT
Platform: UNKNOWN
Requires-Dist: numpy
Requires-Dist: pyparsing (>=2.1.6)
Provides-Extra: test
Requires-Dist: pytest ; extra == 'test'
Requires-Dist: hypothesis ; extra == 'test'
